powerfx/__init__.py
powerfx/__main__.py
powerfx/_loader.py
powerfx/_utility.py
powerfx/engine.py
powerfx/py.typed
powerfx/_bundled/Microsoft.Bcl.AsyncInterfaces.dll
powerfx/_bundled/Microsoft.PowerFx.Core.dll
powerfx/_bundled/Microsoft.PowerFx.Interpreter.dll
powerfx/_bundled/Microsoft.PowerFx.Transport.Attributes.dll
powerfx/_bundled/System.Collections.Immutable.dll
powerfx/_bundled/bg-BG/Microsoft.PowerFx.Core.resources.dll
powerfx/_bundled/bg-BG/Microsoft.PowerFx.Interpreter.resources.dll
powerfx/_bundled/ca-ES/Microsoft.PowerFx.Core.resources.dll
powerfx/_bundled/ca-ES/Microsoft.PowerFx.Interpreter.resources.dll
powerfx/_bundled/cs-CZ/Microsoft.PowerFx.Core.resources.dll
powerfx/_bundled/cs-CZ/Microsoft.PowerFx.Interpreter.resources.dll
powerfx/_bundled/da-DK/Microsoft.PowerFx.Core.resources.dll
powerfx/_bundled/da-DK/Microsoft.PowerFx.Interpreter.resources.dll
powerfx/_bundled/de-DE/Microsoft.PowerFx.Core.resources.dll
powerfx/_bundled/de-DE/Microsoft.PowerFx.Interpreter.resources.dll
powerfx/_bundled/el-GR/Microsoft.PowerFx.Core.resources.dll
powerfx/_bundled/el-GR/Microsoft.PowerFx.Interpreter.resources.dll
powerfx/_bundled/en-US/Microsoft.PowerFx.Core.resources.dll
powerfx/_bundled/en-US/Microsoft.PowerFx.Interpreter.resources.dll
powerfx/_bundled/es-ES/Microsoft.PowerFx.Core.resources.dll
powerfx/_bundled/es-ES/Microsoft.PowerFx.Interpreter.resources.dll
powerfx/_bundled/et-EE/Microsoft.PowerFx.Core.resources.dll
powerfx/_bundled/et-EE/Microsoft.PowerFx.Interpreter.resources.dll
powerfx/_bundled/eu-ES/Microsoft.PowerFx.Core.resources.dll
powerfx/_bundled/eu-ES/Microsoft.PowerFx.Interpreter.resources.dll
powerfx/_bundled/fi-FI/Microsoft.PowerFx.Core.resources.dll
powerfx/_bundled/fi-FI/Microsoft.PowerFx.Interpreter.resources.dll
powerfx/_bundled/fr-FR/Microsoft.PowerFx.Core.resources.dll
powerfx/_bundled/fr-FR/Microsoft.PowerFx.Interpreter.resources.dll
powerfx/_bundled/gl-ES/Microsoft.PowerFx.Core.resources.dll
powerfx-0.0.31.dist-info/licenses/LICENSE
powerfx-0.0.31.dist-info/METADATA
powerfx-0.0.31.dist-info/WHEEL
powerfx-0.0.31.dist-info/top_level.txt
powerfx-0.0.31.dist-info/RECORD
