Metadata-Version: 2.4
Name: powerfx
Version: 0.0.31
Summary: Power Fx python bridge to invoke c# implementation.
Author-email: Microsoft <powerfx-growth@microsoft.com>
Maintainer-email: Microsoft <powerfx-growth@microsoft.com>
License: MIT
Requires-Python: >=3.10
License-File: LICENSE
Requires-Dist: pythonnet==3.0.5
Provides-Extra: dev
Requires-Dist: pytest; extra == "dev"
Requires-Dist: coverage; extra == "dev"
Requires-Dist: ruff; extra == "dev"
Provides-Extra: test
Requires-Dist: coverage; extra == "test"
Requires-Dist: pytest; extra == "test"
Requires-Dist: ruff; extra == "test"
Requires-Dist: ty; extra == "test"
Requires-Dist: ipdb; extra == "test"
Dynamic: license-file
